django_finacc-0.1.2.dist-info/licenses/LICENSE
finacc/__init__.py
finacc/apps.py
finacc/conf.py
finacc/enums.py
finacc/exceptions.py
finacc/init.py
finacc/validators.py
finacc/api/serializers.py
finacc/api/urls.py
finacc/api/views.py
finacc/data/coa_india_basic.json
finacc/data/taxes_india_gst.json
finacc/mgmt/commands/finacc_bootstrap_coa.py
finacc/mgmt/commands/finacc_close_period.py
finacc/mgmt/commands/finacc_seed_fx.py
finacc/models/accounts.py
finacc/models/audit.py
finacc/models/company.py
finacc/models/docs.py
finacc/models/journal.py
finacc/models/period.py
finacc/models/tax.py
finacc/posting/engine.py
finacc/posting/rules.py
finacc/posting/signals.py
finacc/utils/fx.py
finacc/utils/money.py
finacc/utils/periods.py
django_finacc-0.1.2.dist-info/METADATA
django_finacc-0.1.2.dist-info/WHEEL
django_finacc-0.1.2.dist-info/top_level.txt
django_finacc-0.1.2.dist-info/RECORD
