Metadata-Version: 2.4
Name: django-finacc
Version: 0.1.2
Summary: Plug-and-play double-entry accounting for Django (GST, multi-currency, APIViews).
Author-email: "Verified Enquiries / Tushar K." <support@verifiedenquiries.com>
License: MIT
Keywords: django,accounting,double-entry,gst,ledger,trial-balance,finacc
Classifier: Framework :: Django
Classifier: Programming Language :: Python :: 3
Classifier: License :: OSI Approved :: MIT License
Requires-Python: >=3.11
License-File: LICENSE
Requires-Dist: Django>=5.0
Requires-Dist: djangorestframework>=3.15
Dynamic: license-file
